{"matchId":"cecb4a39-76c8-4c76-8b13-9d4c5b8052cf.nakama-0","mapId":"AmbroseValley","date":"February_14","players":[{"userId":"ad5e7f85-e284-4273-988f-532ebd9a5b6d","isBot":false,"events":[{"x":-174.2,"z":333.44,"y":152.16,"ts":1771072306,"event":"Position"},{"x":-170.73,"z":327.54,"y":150.21,"ts":1771072321,"event":"Position"},{"x":-160.8,"z":315.77,"y":147.63,"ts":1771072326,"event":"Position"},{"x":-175.23,"z":313.35,"y":147.52,"ts":1771072331,"event":"Position"},{"x":-175.23,"z":313.35,"y":147.52,"ts":1771072331,"event":"Loot"},{"x":-167.92,"z":307.5,"y":147.52,"ts":1771072336,"event":"Position"},{"x":-153.77,"z":303.42,"y":147.52,"ts":1771072341,"event":"Position"},{"x":-152.88,"z":302.83,"y":147.52,"ts":1771072344,"event":"Loot"},{"x":-152.88,"z":302.83,"y":147.52,"ts":1771072344,"event":"Loot"},{"x":-152.88,"z":302.83,"y":147.52,"ts":1771072344,"event":"Loot"},{"x":-149.72,"z":306.61,"y":147.52,"ts":1771072346,"event":"Position"},{"x":-143.9,"z":291.38,"y":147.91,"ts":1771072351,"event":"Position"},{"x":-145.34,"z":294.38,"y":147.5,"ts":1771072355,"event":"Loot"},{"x":-145.34,"z":294.38,"y":147.5,"ts":1771072356,"event":"Position"},{"x":-139.67,"z":279.56,"y":148.58,"ts":1771072361,"event":"Position"},{"x":-123.42,"z":252.67,"y":136.7,"ts":1771072366,"event":"Position"},{"x":-125.72,"z":249.28,"y":136.71,"ts":1771072371,"event":"Position"},{"x":-125.72,"z":249.28,"y":136.71,"ts":1771072372,"event":"Loot"},{"x":-117.06,"z":244.98,"y":135.53,"ts":1771072376,"event":"Position"},{"x":-108.46,"z":228.81,"y":131.69,"ts":1771072381,"event":"Position"},{"x":-102.05,"z":221.97,"y":129.28,"ts":1771072386,"event":"Position"},{"x":-87.62,"z":206.69,"y":124.43,"ts":1771072396,"event":"Position"},{"x":-69.74,"z":204.07,"y":118.93,"ts":1771072401,"event":"Position"},{"x":-52.04,"z":199.94,"y":114.08,"ts":1771072406,"event":"Position"},{"x":-43.59,"z":183.92,"y":111.68,"ts":1771072411,"event":"Position"},{"x":-43.98,"z":164.81,"y":110.66,"ts":1771072416,"event":"Position"},{"x":-43.53,"z":146.07,"y":109.68,"ts":1771072421,"event":"Position"},{"x":-36.72,"z":131.0,"y":107.99,"ts":1771072426,"event":"Position"},{"x":-32.94,"z":116.12,"y":105.84,"ts":1771072431,"event":"Position"},{"x":-29.19,"z":103.1,"y":103.48,"ts":1771072436,"event":"Position"},{"x":-28.76,"z":98.72,"y":102.95,"ts":1771072440,"event":"BotKill"},{"x":-28.76,"z":98.72,"y":102.95,"ts":1771072442,"event":"Position"},{"x":-25.2,"z":89.09,"y":102.44,"ts":1771072447,"event":"Position"},{"x":-25.2,"z":89.09,"y":102.44,"ts":1771072447,"event":"Loot"},{"x":-25.2,"z":89.09,"y":102.44,"ts":1771072447,"event":"Loot"},{"x":-26.1,"z":77.14,"y":102.31,"ts":1771072452,"event":"Position"},{"x":-36.89,"z":67.22,"y":103.6,"ts":1771072457,"event":"Position"},{"x":-49.65,"z":61.48,"y":101.44,"ts":1771072462,"event":"Position"},{"x":-56.84,"z":61.71,"y":103.12,"ts":1771072467,"event":"Position"},{"x":-58.0,"z":62.12,"y":103.0,"ts":1771072467,"event":"Loot"},{"x":-63.2,"z":56.35,"y":103.0,"ts":1771072472,"event":"Position"},{"x":-71.78,"z":43.7,"y":103.0,"ts":1771072477,"event":"Position"},{"x":-77.32,"z":36.92,"y":103.0,"ts":1771072482,"event":"Position"},{"x":-82.63,"z":23.01,"y":103.0,"ts":1771072487,"event":"Position"},{"x":-94.92,"z":24.65,"y":103.01,"ts":1771072492,"event":"Position"},{"x":-98.36,"z":29.24,"y":103.01,"ts":1771072496,"event":"Loot"},{"x":-98.36,"z":29.24,"y":103.01,"ts":1771072497,"event":"Position"},{"x":-92.33,"z":35.68,"y":103.01,"ts":1771072501,"event":"Loot"},{"x":-94.73,"z":36.24,"y":103.01,"ts":1771072502,"event":"Position"},{"x":-92.14,"z":47.15,"y":103.01,"ts":1771072506,"event":"Loot"},{"x":-92.14,"z":47.15,"y":103.01,"ts":1771072506,"event":"Loot"},{"x":-92.14,"z":47.15,"y":103.01,"ts":1771072507,"event":"Position"},{"x":-84.98,"z":50.03,"y":103.03,"ts":1771072512,"event":"Position"},{"x":-74.33,"z":46.55,"y":103.0,"ts":1771072517,"event":"Position"},{"x":-72.96,"z":45.87,"y":103.0,"ts":1771072522,"event":"BotKilled"}]}]}